CHANGES.rst
CONTRIBUTORS.rst
MANIFEST.in
README.rst
bootstrap.py
buildout.cfg
setup.py
cpskin/__init__.py
cpskin.diazotheme.modern.egg-info/PKG-INFO
cpskin.diazotheme.modern.egg-info/SOURCES.txt
cpskin.diazotheme.modern.egg-info/dependency_links.txt
cpskin.diazotheme.modern.egg-info/entry_points.txt
cpskin.diazotheme.modern.egg-info/namespace_packages.txt
cpskin.diazotheme.modern.egg-info/not-zip-safe
cpskin.diazotheme.modern.egg-info/requires.txt
cpskin.diazotheme.modern.egg-info/top_level.txt
cpskin/diazotheme/__init__.py
cpskin/diazotheme/modern/__init__.py
cpskin/diazotheme/modern/configure.zcml
cpskin/diazotheme/modern/profiles.zcml
cpskin/diazotheme/modern/upgradehandlers.py
cpskin/diazotheme/modern/profiles/default/cssregistry.xml
cpskin/diazotheme/modern/profiles/default/lessregistry.xml
cpskin/diazotheme/modern/profiles/default/metadata.xml
cpskin/diazotheme/modern/profiles/default/theme.xml
cpskin/diazotheme/modern/profiles/uninstall/cssregistry.xml
cpskin/diazotheme/modern/profiles/uninstall/lessregistry.xml
cpskin/diazotheme/modern/static/manifest.cfg
cpskin/diazotheme/modern/static/preview.png
cpskin/diazotheme/modern/static/rules.xml
cpskin/diazotheme/modern/static/css/theme-styles.css
cpskin/diazotheme/modern/static/images/header-bg.jpg
cpskin/diazotheme/modern/static/less/styles.less
cpskin/diazotheme/modern/static/less/variables.less
docs/LICENSE.GPL
docs/LICENSE.rst